<database>
    <name>*dbname*</name>
    <create>true</create>
    <overwrite>false</overwrite>
    <charset>utf8</charset>
    <table>
        <name>*dbprefix*recorder_recordings</name>
        <declaration>
            <field>
                <name>id</name>
                <type>integer</type>
                <notnull>true</notnull>
                <autoincrement>true</autoincrement>
                <unsigned>true</unsigned>
                <primary>true</primary>
                <length>8</length>
            </field>
            <field>
                <name>filename</name>
                <type>text</type>
                <length>1000</length>
                <notnull>true</notnull>
            </field>
            <field>
                <name>owner</name>
                <type>text</type>
                <length>200</length>
                <notnull>true</notnull>
            </field>
            <field>
                <name>uploader</name>
                <type>text</type>
                <length>200</length>
                <notnull>true</notnull>
            </field>
            <field>
                <name>internal_path</name>
                <type>clob</type>
                <notnull>true</notnull>
            </field>
            <field>
                <name>path</name>
                <type>clob</type>
                <notnull>true</notnull>
            </field>
            <field>
                <name>recording_type</name>
                <type>text</type>
                <length>100</length>
                <notnull>true</notnull>
            </field>
            <field>
                <name>upload_time</name>
                <type>datetime</type>
                <notnull>true</notnull>
            </field>
            <field>
                <name>city</name>
                <type>text</type>
                <length>100</length>
                <notnull>true</notnull>
            </field>
            <field>
                <name>region</name>
                <type>text</type>
                <length>100</length>
                <notnull>true</notnull>
            </field>
            <field>
                <name>region_name</name>
                <type>text</type>
                <length>100</length>
                <notnull>true</notnull>
            </field>
            <field>
                <name>country</name>
                <type>text</type>
                <length>100</length>
                <notnull>true</notnull>
            </field>
            <field>
                <name>country_code</name>
                <type>text</type>
                <length>100</length>
                <notnull>true</notnull>
            </field>
            <field>
                <name>timezone</name>
                <type>text</type>
                <length>100</length>
                <notnull>true</notnull>
            </field>
            <field>
                <name>zip</name>
                <type>text</type>
                <length>100</length>
                <notnull>true</notnull>
            </field>
            <field>
                <name>latitude</name>
                <type>float</type>
                <length>10</length>
                <notnull>true</notnull>
            </field>
            <field>
                <name>longitude</name>
                <type>float</type>
                <length>10</length>
                <notnull>true</notnull>
            </field>
            <field>
                <name>content</name>
                <type>clob</type>
                <notnull>true</notnull>
            </field>
            <field>
                <name>is_added_to_map</name>
                <type>boolean</type>
                <notnull>true</notnull>
            </field>
        </declaration>
    </table>
</database>
